webmeter/__main__.py
webmeter/debug.py
webmeter/web.py
webmeter/core/engine.py
webmeter/core/plan.py
webmeter/core/task.py
webmeter/core/utils.py
webmeter/core/file/template.jmx
webmeter/core/jmeter/apache-jmeter-5.6.2/bin/ApacheJMeter.jar
webmeter/core/jmeter/apache-jmeter-5.6.2/bin/BeanShellAssertion.bshrc
webmeter/core/jmeter/apache-jmeter-5.6.2/bin/BeanShellFunction.bshrc
webmeter/core/jmeter/apache-jmeter-5.6.2/bin/BeanShellListeners.bshrc
webmeter/core/jmeter/apache-jmeter-5.6.2/bin/BeanShellSampler.bshrc
webmeter/core/jmeter/apache-jmeter-5.6.2/bin/create-rmi-keystore.bat
webmeter/core/jmeter/apache-jmeter-5.6.2/bin/create-rmi-keystore.sh
webmeter/core/jmeter/apache-jmeter-5.6.2/bin/hc.parameters
webmeter/core/jmeter/apache-jmeter-5.6.2/bin/heapdump.cmd
webmeter/core/jmeter/apache-jmeter-5.6.2/bin/heapdump.sh
webmeter/core/jmeter/apache-jmeter-5.6.2/bin/jaas.conf
webmeter/core/jmeter/apache-jmeter-5.6.2/bin/jmeter
webmeter/core/jmeter/apache-jmeter-5.6.2/bin/jmeter-n-r.cmd
webmeter/core/jmeter/apache-jmeter-5.6.2/bin/jmeter-n.cmd
webmeter/core/jmeter/apache-jmeter-5.6.2/bin/jmeter-server
webmeter/core/jmeter/apache-jmeter-5.6.2/bin/jmeter-server.bat
webmeter/core/jmeter/apache-jmeter-5.6.2/bin/jmeter-t.cmd
webmeter/core/jmeter/apache-jmeter-5.6.2/bin/jmeter.bat
webmeter/core/jmeter/apache-jmeter-5.6.2/bin/jmeter.properties
webmeter/core/jmeter/apache-jmeter-5.6.2/bin/jmeter.sh
webmeter/core/jmeter/apache-jmeter-5.6.2/bin/jmeterw.cmd
webmeter/core/jmeter/apache-jmeter-5.6.2/bin/krb5.conf
webmeter/core/jmeter/apache-jmeter-5.6.2/bin/log4j2.xml
webmeter/core/jmeter/apache-jmeter-5.6.2/bin/mirror-server
webmeter/core/jmeter/apache-jmeter-5.6.2/bin/mirror-server.cmd
webmeter/core/jmeter/apache-jmeter-5.6.2/bin/mirror-server.sh
webmeter/core/jmeter/apache-jmeter-5.6.2/bin/reportgenerator.properties
webmeter/core/jmeter/apache-jmeter-5.6.2/bin/saveservice.properties
webmeter/core/jmeter/apache-jmeter-5.6.2/bin/shutdown.cmd
webmeter-1.0.15.dist-info/LICENSE
webmeter-1.0.15.dist-info/METADATA
webmeter-1.0.15.dist-info/WHEEL
webmeter-1.0.15.dist-info/top_level.txt
webmeter-1.0.15.dist-info/RECORD
