Metadata-Version: 2.1
Name: webmeter
Version: 1.0.15
Summary: WebMeter - A web api-performance tool based on jmeter.
Home-page: https://github.com/rafa0128/webmeter
Author: Rafa Chen
Author-email: laoqi1988_f1@126.com
License: MIT
Classifier: Environment :: Console
Classifier: Intended Audience :: Developers
Classifier: Operating System :: OS Independent
Classifier: Programming Language :: Python :: 3
Requires-Python: >=3.10
License-File: LICENSE
Requires-Dist: fastapi
Requires-Dist: uvicorn
Requires-Dist: requests
Requires-Dist: loguru
Requires-Dist: fire
Requires-Dist: pyfiglet
Requires-Dist: psutil
Requires-Dist: pyyaml
Requires-Dist: python-multipart
Requires-Dist: sqlalchemy
